nocaptchaai_playwright/__init__.py
nocaptchaai_playwright/solver.py
nocaptchaai_playwright-0.1.0.dist-info/LICENSE
nocaptchaai_playwright-0.1.0.dist-info/METADATA
nocaptchaai_playwright-0.1.0.dist-info/WHEEL
nocaptchaai_playwright-0.1.0.dist-info/top_level.txt
nocaptchaai_playwright-0.1.0.dist-info/RECORD
