Metadata-Version: 2.1
Name: nocaptchaai-playwright
Version: 0.1.0
Summary: Playwright implementation of the NoCaptchaAI API
Home-page: https://github.com/claudiofepereira/nocaptchaai-playwright
Author: Cláudio Pereira
License: MIT
Classifier: Development Status :: 4 - Beta
Classifier: Intended Audience :: Developers
Classifier: Natural Language :: English
Classifier: License :: OSI Approved :: MIT License
Classifier: Programming Language :: Python :: 3
Classifier: Programming Language :: Python :: 3.10
Classifier: Topic :: Software Development :: Libraries :: Python Modules
License-File: LICENSE
Requires-Dist: playwright
Requires-Dist: requests
